iotest.py
setup.cfg
setup.py
iotest.egg-info/PKG-INFO
iotest.egg-info/SOURCES.txt
iotest.egg-info/dependency_links.txt
iotest.egg-info/entry_points.txt
iotest.egg-info/requires.txt
iotest.egg-info/top_level.txt