Metadata-Version: 1.1
Name: iotest
Version: 0.1
Summary: iotest is a small tool for testing programs based on input and output.
Home-page: https://github.com/gwk/iotest
Author: George King
Author-email: george.w.king@gmail.com
License: CC0
Keywords: testing
Platform: UNKNOWN
Classifier: Development Status :: 4 - Beta
Classifier: Environment :: Console
Classifier: Intended Audience :: Developers
Classifier: License :: CC0 1.0 Universal (CC0 1.0) Public Domain Dedication
Classifier: Programming Language :: Python :: 3 :: Only
Classifier: Topic :: Software Development :: Testing
